{"_id":"cwru-hubot-scripts","_rev":"3-a4faac771d7945db4bd34ede7d3dfa96","name":"cwru-hubot-scripts","description":"Custom scripts for hubot @ CWRU","dist-tags":{"latest":"0.0.1"},"versions":{"0.0.1":{"author":{"name":"ACM @ CWRU"},"name":"cwru-hubot-scripts","description":"Custom scripts for hubot @ CWRU","version":"0.0.1","repository":{"url":"git://github.com/hacsoc/cwru-hubot-scripts.git"},"engines":{"node":"*"},"readme":"Scripts for CWRU's hubot\n","readmeFilename":"README.md","_id":"cwru-hubot-scripts@0.0.1","dist":{"shasum":"c6bfad4150bafa44ac43d069deb228b7db436cf9","tarball":"https://registry.npmjs.org/cwru-hubot-scripts/-/cwru-hubot-scripts-0.0.1.tgz"},"_from":".","_npmVersion":"1.2.2","_npmUser":{"name":"tdooner","email":"ted27@case.edu"},"maintainers":[{"name":"tdooner","email":"ted27@case.edu"}],"directories":{}}},"readme":"Scripts for CWRU's hubot\n","maintainers":[{"name":"tdooner","email":"ted27@case.edu"}],"time":{"modified":"2013-01-29T03:48:47.799Z","created":"2013-01-29T03:48:47.096Z","0.0.1":"2013-01-29T03:48:47.799Z"},"author":{"name":"ACM @ CWRU"},"repository":{"url":"git://github.com/hacsoc/cwru-hubot-scripts.git"},"_attachments":{}}