{"_id":"hubot-rollcall","_rev":"6-3ab656740c0ec3beb31ced4a4503d1da","name":"hubot-rollcall","description":"Rollcall functionality for hubot","dist-tags":{"latest":"0.1.5"},"versions":{"0.1.0":{"main":"index.coffee","author":{"name":"J.B. Zimmerman"},"name":"hubot-rollcall","description":"Rollcall functionality for hubot","license":"MIT","version":"0.1.0","homepage":"https://github.com/jbz/hubot-rollcall","repository":{"type":"git","url":"git://github.com/jbz/hubot-rollcall.git"},"engines":{"node":"> 0.6.0"},"devDependencies":{"coffee-script":"~1.6","mocha":"*","chai":"*","sinon-chai":"*","sinon":"*","matchdep":"~0.1.2"},"scripts":{"bootstrap":"scripts/bootstrap","test":"scripts/test"},"gitHead":"f5385113f1ce28ff25cc842f47f86756614c2edf","bugs":{"url":"https://github.com/jbz/hubot-rollcall/issues"},"_id":"hubot-rollcall@0.1.0","_shasum":"29f7c48d7a00eaaacda82a221bbe4863687a4a3a","_from":".","_npmVersion":"3.10.5","_nodeVersion":"0.12.7","_npmUser":{"name":"jbz","email":"jbzimmerman91@gmail.com"},"dist":{"shasum":"29f7c48d7a00eaaacda82a221bbe4863687a4a3a","tarball":"https://registry.npmjs.org/hubot-rollcall/-/hubot-rollcall-0.1.0.tgz"},"maintainers":[{"name":"jbz","email":"jbzimmerman91@gmail.com"}],"_npmOperationalInternal":{"host":"packages-16-east.internal.npmjs.com","tmp":"tmp/hubot-rollcall-0.1.0.tgz_1469728366956_0.3966611544601619"},"directories":{}},"0.1.1":{"main":"index.coffee","author":{"name":"J.B. Zimmerman"},"name":"hubot-rollcall","description":"Rollcall functionality for hubot","license":"MIT","version":"0.1.1","homepage":"https://github.com/jbz/hubot-rollcall","repository":{"type":"git","url":"git://github.com/jbz/hubot-rollcall.git"},"engines":{"node":"> 0.6.0"},"devDependencies":{"coffee-script":"~1.6","mocha":"*","chai":"*","sinon-chai":"*","sinon":"*","matchdep":"~0.1.2"},"scripts":{"bootstrap":"scripts/bootstrap","test":"scripts/test"},"gitHead":"81b00541439c541170222fef3b6cfe2fac120cdb","bugs":{"url":"https://github.com/jbz/hubot-rollcall/issues"},"_id":"hubot-rollcall@0.1.1","_shasum":"ca2a6015d9f777bae2a536f370a83874555ebcac","_from":".","_npmVersion":"3.10.5","_nodeVersion":"6.3.1","_npmUser":{"name":"jbz","email":"jbzimmerman91@gmail.com"},"dist":{"shasum":"ca2a6015d9f777bae2a536f370a83874555ebcac","tarball":"https://registry.npmjs.org/hubot-rollcall/-/hubot-rollcall-0.1.1.tgz"},"maintainers":[{"name":"jbz","email":"jbzimmerman91@gmail.com"}],"_npmOperationalInternal":{"host":"packages-12-west.internal.npmjs.com","tmp":"tmp/hubot-rollcall-0.1.1.tgz_1469827304861_0.49637829465791583"},"directories":{}},"0.1.2":{"main":"index.coffee","author":{"name":"J.B. Zimmerman"},"name":"hubot-rollcall","description":"Rollcall functionality for hubot","license":"MIT","version":"0.1.2","homepage":"https://github.com/jbz/hubot-rollcall","repository":{"type":"git","url":"git://github.com/jbz/hubot-rollcall.git"},"engines":{"node":"> 0.6.0"},"devDependencies":{"coffee-script":"~1.6","mocha":"*","chai":"*","sinon-chai":"*","sinon":"*","matchdep":"~0.1.2"},"scripts":{"bootstrap":"scripts/bootstrap","test":"scripts/test"},"gitHead":"1e3549b896d14dc3a3c3e935a21d1c2e68ca3166","bugs":{"url":"https://github.com/jbz/hubot-rollcall/issues"},"_id":"hubot-rollcall@0.1.2","_shasum":"d44b9eddb5f7b6e9ba6a365d91d874ab2330c799","_from":".","_npmVersion":"3.10.5","_nodeVersion":"6.3.1","_npmUser":{"name":"jbz","email":"jbzimmerman91@gmail.com"},"dist":{"shasum":"d44b9eddb5f7b6e9ba6a365d91d874ab2330c799","tarball":"https://registry.npmjs.org/hubot-rollcall/-/hubot-rollcall-0.1.2.tgz"},"maintainers":[{"name":"jbz","email":"jbzimmerman91@gmail.com"}],"_npmOperationalInternal":{"host":"packages-16-east.internal.npmjs.com","tmp":"tmp/hubot-rollcall-0.1.2.tgz_1471288272452_0.06775450869463384"},"directories":{}},"0.1.3":{"main":"index.coffee","author":{"name":"J.B. Zimmerman"},"name":"hubot-rollcall","description":"Rollcall functionality for hubot","license":"MIT","version":"0.1.3","homepage":"https://github.com/jbz/hubot-rollcall","repository":{"type":"git","url":"git://github.com/jbz/hubot-rollcall.git"},"engines":{"node":"> 0.6.0"},"devDependencies":{"coffee-script":"~1.6","mocha":"*","chai":"*","sinon-chai":"*","sinon":"*","matchdep":"~0.1.2"},"scripts":{"bootstrap":"scripts/bootstrap","test":"scripts/test"},"gitHead":"3e1ae8b4cb14e0dfea13781876f37f31ec50c9b9","bugs":{"url":"https://github.com/jbz/hubot-rollcall/issues"},"_id":"hubot-rollcall@0.1.3","_shasum":"eb86cc8e0a3dff115f5b45efef8cf9db8f4a08f4","_from":".","_npmVersion":"3.10.5","_nodeVersion":"6.3.1","_npmUser":{"name":"jbz","email":"jbzimmerman91@gmail.com"},"dist":{"shasum":"eb86cc8e0a3dff115f5b45efef8cf9db8f4a08f4","tarball":"https://registry.npmjs.org/hubot-rollcall/-/hubot-rollcall-0.1.3.tgz"},"maintainers":[{"name":"jbz","email":"jbzimmerman91@gmail.com"}],"_npmOperationalInternal":{"host":"packages-16-east.internal.npmjs.com","tmp":"tmp/hubot-rollcall-0.1.3.tgz_1471901269367_0.7868990963324904"},"directories":{}},"0.1.4":{"main":"index.coffee","author":{"name":"J.B. Zimmerman"},"name":"hubot-rollcall","description":"Rollcall functionality for hubot","license":"MIT","version":"0.1.4","homepage":"https://github.com/jbz/hubot-rollcall","repository":{"type":"git","url":"git://github.com/jbz/hubot-rollcall.git"},"engines":{"node":"> 0.6.0"},"devDependencies":{"coffee-script":"~1.6","mocha":"*","chai":"*","sinon-chai":"*","sinon":"*","matchdep":"~0.1.2"},"scripts":{"bootstrap":"scripts/bootstrap","test":"scripts/test"},"gitHead":"a82877e12b3fb67bac7a3a80029c2233cfe6d4d9","bugs":{"url":"https://github.com/jbz/hubot-rollcall/issues"},"_id":"hubot-rollcall@0.1.4","_shasum":"6f17e43b7a49761a48efa10247ca48ec49d94165","_from":".","_npmVersion":"3.10.7","_nodeVersion":"6.7.0","_npmUser":{"name":"jbz","email":"jbzimmerman91@gmail.com"},"dist":{"shasum":"6f17e43b7a49761a48efa10247ca48ec49d94165","tarball":"https://registry.npmjs.org/hubot-rollcall/-/hubot-rollcall-0.1.4.tgz"},"maintainers":[{"name":"jbz","email":"jbzimmerman91@gmail.com"}],"_npmOperationalInternal":{"host":"packages-12-west.internal.npmjs.com","tmp":"tmp/hubot-rollcall-0.1.4.tgz_1482874021481_0.6352735753171146"},"directories":{}},"0.1.5":{"main":"index.coffee","author":{"name":"J.B. Zimmerman"},"name":"hubot-rollcall","description":"Rollcall functionality for hubot","license":"MIT","version":"0.1.5","homepage":"https://github.com/jbz/hubot-rollcall","repository":{"type":"git","url":"git://github.com/jbz/hubot-rollcall.git"},"engines":{"node":"> 0.6.0"},"devDependencies":{"coffee-script":"~1.6","mocha":"*","chai":"*","sinon-chai":"*","sinon":"*","matchdep":"~0.1.2"},"scripts":{"bootstrap":"scripts/bootstrap","test":"scripts/test"},"gitHead":"0ed12c26a902563552691050ecc42484f3e40616","bugs":{"url":"https://github.com/jbz/hubot-rollcall/issues"},"_id":"hubot-rollcall@0.1.5","_shasum":"66bab622b90d7bf88b403df3ec04f8c0e31bed26","_from":".","_npmVersion":"3.10.7","_nodeVersion":"6.7.0","_npmUser":{"name":"jbz","email":"jbzimmerman91@gmail.com"},"dist":{"shasum":"66bab622b90d7bf88b403df3ec04f8c0e31bed26","tarball":"https://registry.npmjs.org/hubot-rollcall/-/hubot-rollcall-0.1.5.tgz"},"maintainers":[{"name":"jbz","email":"jbzimmerman91@gmail.com"}],"_npmOperationalInternal":{"host":"packages-12-west.internal.npmjs.com","tmp":"tmp/hubot-rollcall-0.1.5.tgz_1482874678822_0.07127077574841678"},"directories":{}}},"readme":"# hubot-rollcall\n\nAttendance taking functionality for [hubot](https://github.com/github/hubot).\nCoffeescript and hubot teachings gratefully taken from [hubot-standup](https://github.com/miyagawa/hubot-standup), amongst other places.\nAt present, only tested on Slack (username handling is probably Slack-centric).\n\n## How to use\n\nCreate a room (or channel on IRC) for rollcall and invite hubot to the room if necessary.\n\n### Start the rollcall\n\nYou start the rollcall by telling hubot to start one and giving it a list of users who\nyou would like to confirm are present. Usernames must begin with a '@' or rollcall will\nignore them. Rollcall will also deduplicate the username list.\n\n```\njbz: hubot rollcall start @jbz @ianw @zach @jbz\nhubot: Starting a rollcall for the following attendees: @jbz @ianw @zach\n```\n\n### Confirming your presence\n\nTell the robot you're here.\n\n```\njbz: hubot here\nhubot: @jbz is here! (1/3) are here!\n```\n\n### Stand-ins\n\nYou can stand in for an attendee by saying 'sub for <user>' or 'stand-in for <user>'.\n\n```\nlolo: hubot sub for @zach\nhubot: @lolo is standing in for @zach! (2/3) are here! \n```\n\n### Checking on status\n\nAt any time, you can ask hubot who has not yet checked in.\n\n```\njbz: hubot rollcall status\nhubot: Rollcall in progress.  Waiting for 1 of 3 participants - @ianw\n```\n\n### Completion\n\nWhen the last person (or stand-in) checks in, the rollcall will be announced complete.\n\n```\nianw:  hubot present\nhubot: @ianw is here!\nhubot: (3/3) present or accounted for!\nhubot: Attendance check COMPLETED at 07/27 14:17\n```\n\n### Canceling the rollcall\n\nEach channel/room can only have one rollcall ongoing at a time.  If you try to start\nanother before completing/canceling the first, you'll get an error message:\n\n```\nianw: hubot rollcall start @jbz @zach\nhubot: There is already a rollcall in progress here!  Cancel it first with 'hubot rollcall cancel'\n```\n \n## Author\n\n[J.B. Zimmerman](https://github.com/jbz)\n\n## License\n\nMIT License\n","maintainers":[{"name":"jbz","email":"jbzimmerman91@gmail.com"}],"time":{"modified":"2016-12-27T21:37:59.070Z","created":"2016-07-28T17:52:49.703Z","0.1.0":"2016-07-28T17:52:49.703Z","0.1.1":"2016-07-29T21:21:46.521Z","0.1.2":"2016-08-15T19:11:14.404Z","0.1.3":"2016-08-22T21:27:51.299Z","0.1.4":"2016-12-27T21:27:01.724Z","0.1.5":"2016-12-27T21:37:59.070Z"},"homepage":"https://github.com/jbz/hubot-rollcall","repository":{"type":"git","url":"git://github.com/jbz/hubot-rollcall.git"},"author":{"name":"J.B. Zimmerman"},"bugs":{"url":"https://github.com/jbz/hubot-rollcall/issues"},"license":"MIT","readmeFilename":"README.md","_attachments":{}}