{"_id":"hubot-laclasse","_rev":"8-156d5f188b1bafbc38658b67fcfcd8cd","name":"hubot-laclasse","description":"Paste quotes from La Classe Américaine","dist-tags":{"latest":"0.0.4"},"versions":{"0.0.1":{"name":"hubot-laclasse","version":"0.0.1","description":"Paste quotes from La Classe Américaine","main":"./lib/index.coffee","author":{"name":"François de Metz"},"license":"BSD","dependencies":{"jsdom":""},"_id":"hubot-laclasse@0.0.1","dist":{"shasum":"556251a9b590a12afde2e6f17888884016cdab4d","tarball":"https://registry.npmjs.org/hubot-laclasse/-/hubot-laclasse-0.0.1.tgz"},"_from":".","_npmVersion":"1.2.10","_npmUser":{"name":"francois","email":"francois@2metz.fr"},"maintainers":[{"name":"francois","email":"francois@2metz.fr"}],"directories":{}},"0.0.2":{"name":"hubot-laclasse","version":"0.0.2","description":"Paste quotes from La Classe Américaine","main":"./lib/index.coffee","author":{"name":"François de Metz"},"license":"BSD","dependencies":{"jsdom":""},"_id":"hubot-laclasse@0.0.2","dist":{"shasum":"852082aff52ae11e8372a7aaf07a8db1fb648b49","tarball":"https://registry.npmjs.org/hubot-laclasse/-/hubot-laclasse-0.0.2.tgz"},"_from":".","_npmVersion":"1.2.10","_npmUser":{"name":"francois","email":"francois@2metz.fr"},"maintainers":[{"name":"francois","email":"francois@2metz.fr"}],"directories":{}},"0.0.3":{"name":"hubot-laclasse","version":"0.0.3","description":"Paste quotes from La Classe Américaine","main":"./lib/index.coffee","author":{"name":"François de Metz"},"license":"BSD","dependencies":{"jsdom":""},"_id":"hubot-laclasse@0.0.3","dist":{"shasum":"bb4edb3bc0f988c195c720615b535b04082b5f0e","tarball":"https://registry.npmjs.org/hubot-laclasse/-/hubot-laclasse-0.0.3.tgz"},"_from":".","_npmVersion":"1.2.10","_npmUser":{"name":"francois","email":"francois@2metz.fr"},"maintainers":[{"name":"francois","email":"francois@2metz.fr"}],"directories":{}},"0.0.4":{"name":"hubot-laclasse","version":"0.0.4","description":"Paste quotes from La Classe Américaine","main":"./lib/index.coffee","author":{"name":"François de Metz"},"license":"BSD","repository":{"type":"git","url":"git+https://github.com/francois2metz/hubot-laclasse.git"},"dependencies":{"jsdom":"~3.1.x"},"gitHead":"9f8551cf917972d0f118a2002377f83f96206c19","bugs":{"url":"https://github.com/francois2metz/hubot-laclasse/issues"},"homepage":"https://github.com/francois2metz/hubot-laclasse#readme","_id":"hubot-laclasse@0.0.4","scripts":{},"_shasum":"117d7cfb21997fdb46fff1126ab3c0a85b5f2636","_from":".","_npmVersion":"2.13.3","_nodeVersion":"3.2.0","_npmUser":{"name":"francois","email":"francois@2metz.fr"},"dist":{"shasum":"117d7cfb21997fdb46fff1126ab3c0a85b5f2636","tarball":"https://registry.npmjs.org/hubot-laclasse/-/hubot-laclasse-0.0.4.tgz"},"maintainers":[{"name":"francois","email":"francois@2metz.fr"}],"directories":{}}},"readme":"# Hubot La Classe Américaine\n\nIf like me you love [La Classe Américaine](http://cyclim.se/), you probably quote sometimes the scenario.\n\nThis hubot script do exactly that!\n\n> francois: http://cyclim.se/script.html#0:28:47\n>\n> hubot:  George — Si tu veux me parler, envoie-moi un… fax !\n\n## Install\n\nAdd hubot-laclasse to your *package.json*.\n\n    npm install --save hubot-laclasse\n\nThen add hubot-laclasse to  *external_scripts.json*.\n\n```javascript\n[..., \"hubot-laclasse\", ...]\n```\n\n## License\n\nCopyright (c) 2013 François de Metz\n\nSee [LICENSE](LICENSE).\n","maintainers":[{"name":"francois","email":"francois@2metz.fr"}],"time":{"modified":"2015-09-03T14:17:41.362Z","created":"2013-10-28T12:49:59.414Z","0.0.1":"2013-10-28T12:50:01.287Z","0.0.2":"2013-10-28T12:55:09.556Z","0.0.3":"2013-10-28T13:55:54.539Z","0.0.4":"2015-09-03T14:17:41.362Z"},"author":{"name":"François de Metz"},"homepage":"https://github.com/francois2metz/hubot-laclasse#readme","repository":{"type":"git","url":"git+https://github.com/francois2metz/hubot-laclasse.git"},"bugs":{"url":"https://github.com/francois2metz/hubot-laclasse/issues"},"license":"BSD","readmeFilename":"README.md","_attachments":{}}