{"_id":"hubot-jobscheduler","_rev":"2-ec6ff10ec661cbbdcbfe216060272986","name":"hubot-jobscheduler","description":"Hubot script for opration to JobScheduler","dist-tags":{"latest":"0.0.2"},"versions":{"0.0.1":{"name":"hubot-jobscheduler","version":"0.0.1","description":"Hubot script for opration to JobScheduler","dependencies":{"jobscheduler":">0.0.0"},"main":"index.coffee","repository":{"type":"git","url":"git+https://github.com/ike-dai/hubot-jobscheduler.git"},"license":"Apache-2.0","author":{"name":"Daisuke IKEDA"},"gitHead":"a9e698d2b14e4977ac47fc37ecb69ca444a2ecd1","bugs":{"url":"https://github.com/ike-dai/hubot-jobscheduler/issues"},"homepage":"https://github.com/ike-dai/hubot-jobscheduler#readme","_id":"hubot-jobscheduler@0.0.1","scripts":{},"_shasum":"318d104ab33bd3c5af513c9b6675aa1487f367bc","_from":".","_npmVersion":"3.3.9","_nodeVersion":"5.0.0","_npmUser":{"name":"ike-dai","email":"dai.ikd123@gmail.com"},"dist":{"shasum":"318d104ab33bd3c5af513c9b6675aa1487f367bc","tarball":"https://registry.npmjs.org/hubot-jobscheduler/-/hubot-jobscheduler-0.0.1.tgz"},"maintainers":[{"name":"ike-dai","email":"dai.ikd123@gmail.com"}],"_npmOperationalInternal":{"host":"packages-16-east.internal.npmjs.com","tmp":"tmp/hubot-jobscheduler-0.0.1.tgz_1476200368714_0.061563381692394614"},"directories":{}},"0.0.2":{"name":"hubot-jobscheduler","version":"0.0.2","description":"Hubot script for opration to JobScheduler","dependencies":{"jobscheduler":">0.0.0"},"main":"index.coffee","repository":{"type":"git","url":"git+https://github.com/ike-dai/hubot-jobscheduler.git"},"license":"Apache-2.0","author":{"name":"Daisuke IKEDA"},"gitHead":"960942dd6bdd2512698f80455974573af56a61d7","bugs":{"url":"https://github.com/ike-dai/hubot-jobscheduler/issues"},"homepage":"https://github.com/ike-dai/hubot-jobscheduler#readme","_id":"hubot-jobscheduler@0.0.2","scripts":{},"_shasum":"1930c57613af78e0e3afd3b87c0a3db0c4264c72","_from":".","_npmVersion":"3.3.9","_nodeVersion":"5.0.0","_npmUser":{"name":"ike-dai","email":"dai.ikd123@gmail.com"},"dist":{"shasum":"1930c57613af78e0e3afd3b87c0a3db0c4264c72","tarball":"https://registry.npmjs.org/hubot-jobscheduler/-/hubot-jobscheduler-0.0.2.tgz"},"maintainers":[{"name":"ike-dai","email":"dai.ikd123@gmail.com"}],"_npmOperationalInternal":{"host":"packages-18-east.internal.npmjs.com","tmp":"tmp/hubot-jobscheduler-0.0.2.tgz_1476856822259_0.7409200614783913"},"directories":{}}},"readme":"# Hubot JobScheduler sample script\n\n## What?\n\nThis is [JobScheuler](http://www.sos-berlin.com/jobscheduler) collaboration hubot script.\n\n## Supported hubot command\n\n* hubot set url <JOC url> \n    * This command should be executed at first.\n    * URL is set on hubot brain\n* hubot start job <job name>\n    * This command execute JobScheduler job\n\n## Supported JobScheduler version\n\n* v.1.10\n\n## How to use\n\n```\n$ npm install hubot-jobscheduler\n$ vim external-scripts.json\n[\n    \"hubot-xxxx\",\n    \"hubot-yyyy\",\n    ....,\n    \"hubot-jobscheduler\"\n]\n```\n\n\n## Contact\n\nPlease send feedback to me.\nDaisuke IKEDA\n\nTwitter: [@ike_dai](https://twitter.com/ike_dai)\ne-mail: <dai.ikd123@gmail.com>\n\n## License\n\nLicensed under the Apache License, Version 2.0. The Apache v2 full text is published at this [link](http://www.apache.org/licenses/LICENSE-2.0).\n\nCopyright 2016 Daisuke IKEDA.\n","maintainers":[{"name":"ike-dai","email":"dai.ikd123@gmail.com"}],"time":{"modified":"2016-10-19T06:00:24.093Z","created":"2016-10-11T15:39:30.273Z","0.0.1":"2016-10-11T15:39:30.273Z","0.0.2":"2016-10-19T06:00:24.093Z"},"homepage":"https://github.com/ike-dai/hubot-jobscheduler#readme","repository":{"type":"git","url":"git+https://github.com/ike-dai/hubot-jobscheduler.git"},"author":{"name":"Daisuke IKEDA"},"bugs":{"url":"https://github.com/ike-dai/hubot-jobscheduler/issues"},"license":"Apache-2.0","readmeFilename":"README.md","_attachments":{}}