{"_id":"hubot-delve","_rev":"5-4347cfd2902fcb9863a83294c201285c","name":"hubot-delve","dist-tags":{"latest":"1.3.1"},"versions":{"1.0.0":{"name":"hubot-delve","version":"1.0.0","description":"","main":"src/delve.coffee","scripts":{"test":"echo \"Error: no test specified\" && exit 1"},"author":"","dependencies":{"parent-require":"^1.0.0"},"peerDependencies":{"hubot":">=2.0"},"devDependencies":{"coffee-script":">=1.2.0"},"license":"ISC","gitHead":"90aa07960d3108741f1e62bd394fc9ea7de795eb","_id":"hubot-delve@1.0.0","_shasum":"c70c16bb9ee3a8d284f12ac15a451c6d5f7f4b9a","_from":".","_npmVersion":"3.8.8","_nodeVersion":"6.0.0","_npmUser":{"name":"nicolai.bodd","email":"nicolaib@microsoft.com"},"dist":{"shasum":"c70c16bb9ee3a8d284f12ac15a451c6d5f7f4b9a","tarball":"https://registry.npmjs.org/hubot-delve/-/hubot-delve-1.0.0.tgz"},"maintainers":[{"name":"nicolai.bodd","email":"nicolaib@microsoft.com"}],"_npmOperationalInternal":{"host":"packages-12-west.internal.npmjs.com","tmp":"tmp/hubot-delve-1.0.0.tgz_1463259283088_0.5457936797756702"},"directories":{}},"1.1.0":{"name":"hubot-delve","version":"1.1.0","description":"","main":"src/delve.coffee","scripts":{"test":"echo \"Error: no test specified\" && exit 1"},"author":"","devDependencies":{"coffee-script":">=1.2.0"},"license":"ISC","gitHead":"99f60843c3f613e679275b2fa9f18ef7471672ac","_id":"hubot-delve@1.1.0","_shasum":"e04946553b2783bc4b78e3a5faf2d7701bc9eb07","_from":".","_npmVersion":"3.8.8","_nodeVersion":"6.0.0","_npmUser":{"name":"nicolai.bodd","email":"nicolaib@microsoft.com"},"dist":{"shasum":"e04946553b2783bc4b78e3a5faf2d7701bc9eb07","tarball":"https://registry.npmjs.org/hubot-delve/-/hubot-delve-1.1.0.tgz"},"maintainers":[{"name":"nicolai.bodd","email":"nicolaib@microsoft.com"}],"_npmOperationalInternal":{"host":"packages-16-east.internal.npmjs.com","tmp":"tmp/hubot-delve-1.1.0.tgz_1463303747246_0.15325697232037783"},"directories":{}},"1.2.0":{"name":"hubot-delve","version":"1.2.0","description":"","main":"src/delve.coffee","scripts":{"test":"echo \"Error: no test specified\" && exit 1"},"author":"","devDependencies":{"coffee-script":">=1.2.0"},"license":"ISC","dependencies":{"request":"^2.72.0"},"gitHead":"99f60843c3f613e679275b2fa9f18ef7471672ac","_id":"hubot-delve@1.2.0","_shasum":"71279b945f892229168aaef33a004a58dc827edb","_from":".","_npmVersion":"3.8.8","_nodeVersion":"6.0.0","_npmUser":{"name":"nicolai.bodd","email":"nicolaib@microsoft.com"},"dist":{"shasum":"71279b945f892229168aaef33a004a58dc827edb","tarball":"https://registry.npmjs.org/hubot-delve/-/hubot-delve-1.2.0.tgz"},"maintainers":[{"name":"nicolai.bodd","email":"nicolaib@microsoft.com"}],"_npmOperationalInternal":{"host":"packages-12-west.internal.npmjs.com","tmp":"tmp/hubot-delve-1.2.0.tgz_1463304496547_0.20902702352032065"},"directories":{}},"1.3.0":{"name":"hubot-delve","version":"1.3.0","description":"","main":"src/delve.coffee","scripts":{"test":"echo \"Error: no test specified\" && exit 1"},"author":"","devDependencies":{"coffee-script":">=1.2.0"},"license":"ISC","dependencies":{"request":"^2.72.0"},"gitHead":"2bcd9a8cd6c79237661fb6aaefca4e60de6196da","_id":"hubot-delve@1.3.0","_shasum":"ff4991f2bf3fd029f78e5b64d6c4c9af74903539","_from":".","_npmVersion":"3.8.8","_nodeVersion":"6.0.0","_npmUser":{"name":"nicolai.bodd","email":"nicolaib@microsoft.com"},"dist":{"shasum":"ff4991f2bf3fd029f78e5b64d6c4c9af74903539","tarball":"https://registry.npmjs.org/hubot-delve/-/hubot-delve-1.3.0.tgz"},"maintainers":[{"name":"nicolai.bodd","email":"nicolaib@microsoft.com"}],"_npmOperationalInternal":{"host":"packages-12-west.internal.npmjs.com","tmp":"tmp/hubot-delve-1.3.0.tgz_1463613290127_0.7281457567587495"},"directories":{}},"1.3.1":{"name":"hubot-delve","version":"1.3.1","description":"The hubot adapter for caap","main":"src/delve.coffee","scripts":{"test":"echo \"Error: no test specified\" && exit 1"},"author":"","devDependencies":{"coffee-script":">=1.2.0"},"license":"ISC","dependencies":{"request":"^2.72.0"},"gitHead":"2237aee8c257633712e304196e35f328b23148af","_id":"hubot-delve@1.3.1","_shasum":"86ca01c5eefe130579577d86b1d50470e9a316f4","_from":".","_npmVersion":"3.10.9","_nodeVersion":"7.2.0","_npmUser":{"name":"nicolai.bodd","email":"nicolaib@microsoft.com"},"dist":{"shasum":"86ca01c5eefe130579577d86b1d50470e9a316f4","tarball":"https://registry.npmjs.org/hubot-delve/-/hubot-delve-1.3.1.tgz"},"maintainers":[{"name":"nicolai.bodd","email":"nicolaib@microsoft.com"}],"_npmOperationalInternal":{"host":"packages-18-east.internal.npmjs.com","tmp":"tmp/hubot-delve-1.3.1.tgz_1484156880602_0.7943422342650592"},"directories":{}}},"readme":"# hubot-delve\r\n\r\nThe hubot adapter for caap\r\n\r\n","maintainers":[{"name":"nicolai.bodd","email":"nicolaib@microsoft.com"}],"time":{"modified":"2017-01-11T17:48:01.268Z","created":"2016-05-14T20:54:45.368Z","1.0.0":"2016-05-14T20:54:45.368Z","1.1.0":"2016-05-15T09:15:49.163Z","1.2.0":"2016-05-15T09:28:18.910Z","1.3.0":"2016-05-18T23:14:52.522Z","1.3.1":"2017-01-11T17:48:01.268Z"},"license":"ISC","readmeFilename":"README.md","description":"The hubot adapter for caap","_attachments":{}}